{
    "content": "sum of two numbers",
    "description": "Detailed information about the coding question",
    "difficultyLevel": 1,
    "constraints": [
      {
        "constraint": "Detailed information of constraint"
      }
    ],
    "method": {
      "methodName": "AddTwoNumbers",
      "arguments": [
        {
          "argumentName": "num1",
          "argumentPosition": 1,
          "argumentDataType": {
            "dataTypeId": 1
          }
        },
        {
          "argumentName": "num2",
          "argumentPosition": 2,
          "argumentDataType": {
            "dataTypeId": 1
          }
        }
      ],
      "returnType":{
          "dataTypeId": 1
        }
    },
  
    "testCases": [
      {
        "isSample": true,
        "expectedResult": "5",
        "exampleExplainAction": "This is an example test case.",
        "inputs": [
          {
            "inputValue": "2",
            "arguments": {
              "argumentName": "num1"
            }
          },
          {
            "inputValue": "3",
            "arguments": {
              "argumentName": "num2"
            }
          }
        ]
      },
      {
        "isSample": true,
        "expectedResult": "10",
        "exampleExplainAction": "This is an example test case.",
        "inputs": [
          {
            "inputValue": "5",
            "arguments": {
              "argumentName": "num1"
            }
          },
          {
            "inputValue": "5",
            "arguments": {
              "argumentName": "num2"
            }
          }
        ]
      }
    ]
  }
  


